face_compare/__init__.py
face_compare/images.py
face_compare/model.py
face_compare/weights/__init__.py
face_compare/weights/facenet_weights.h5
face_compare/weights/weights.py
face_compare-1.1.4.data/scripts/compare_faces.py
face_compare-1.1.4.dist-info/LICENSE
face_compare-1.1.4.dist-info/METADATA
face_compare-1.1.4.dist-info/WHEEL
face_compare-1.1.4.dist-info/top_level.txt
face_compare-1.1.4.dist-info/RECORD
