Metadata-Version: 2.1
Name: face-compare
Version: 1.1.4
Summary: Compare if two faces are from the same person.
Home-page: https://github.com/mattlyon93/face-comparison
Download-URL: https://github.com/mattlyon93/face-comparison/archive/v1.1.4.tar.gz
Author: Matt Lyon
Author-email: matthewlyon18@gmail.com
License: MIT License
Keywords: ai,cv,computer-vision,face-detection
Classifier: Programming Language :: Python
Classifier: Operating System :: Unix
Classifier: Operating System :: MacOS
Requires-Python: >=3.7
License-File: LICENSE
Requires-Dist: numpy
Requires-Dist: tensorflow (==2.9.3)
Requires-Dist: scipy
Requires-Dist: opencv-python
